{
  "fund": {
    "id": "00981A",
    "name": "統一台股增長",
    "fund_code": "49YTW",
    "url": "https://www.ezmoney.com.tw/ETF/Fund/Info?FundCode=49YTW",
    "source": "EZMoney"
  },
  "month": "2026-05",
  "snapshots": [
    {
      "snapshot_date": "2026-05-01",
      "holdings_count": 50,
      "top_holdings": [
        {
          "code": "2330",
          "name": "台積電",
          "shares": 10039000.0,
          "weight": "8.970%",
          "weight_value": 8.97,
          "rank": 1
        },
        {
          "code": "2383",
          "name": "台光電",
          "shares": 4425000.0,
          "weight": "8.420%",
          "weight_value": 8.42,
          "rank": 2
        },
        {
          "code": "2345",
          "name": "智邦",
          "shares": 6031000.0,
          "weight": "5.750%",
          "weight_value": 5.75,
          "rank": 3
        },
        {
          "code": "2308",
          "name": "台達電",
          "shares": 6024000.0,
          "weight": "5.460%",
          "weight_value": 5.46,
          "rank": 4
        },
        {
          "code": "8046",
          "name": "南電",
          "shares": 12637000.0,
          "weight": "5.320%",
          "weight_value": 5.32,
          "rank": 5
        },
        {
          "code": "3665",
          "name": "貿聯-KY",
          "shares": 4583848.0,
          "weight": "5.310%",
          "weight_value": 5.31,
          "rank": 6
        },
        {
          "code": "3653",
          "name": "健策",
          "shares": 2267000.0,
          "weight": "5.100%",
          "weight_value": 5.1,
          "rank": 7
        },
        {
          "code": "2368",
          "name": "金像電",
          "shares": 8240000.0,
          "weight": "4.790%",
          "weight_value": 4.79,
          "rank": 8
        },
        {
          "code": "2454",
          "name": "聯發科",
          "shares": 4363000.0,
          "weight": "4.770%",
          "weight_value": 4.77,
          "rank": 9
        },
        {
          "code": "3017",
          "name": "奇鋐",
          "shares": 3902000.0,
          "weight": "4.630%",
          "weight_value": 4.63,
          "rank": 10
        }
      ]
    },
    {
      "snapshot_date": "2026-05-02",
      "holdings_count": 50,
      "top_holdings": [
        {
          "code": "2330",
          "name": "台積電",
          "shares": 10039000.0,
          "weight": "8.970%",
          "weight_value": 8.97,
          "rank": 1
        },
        {
          "code": "2383",
          "name": "台光電",
          "shares": 4425000.0,
          "weight": "8.420%",
          "weight_value": 8.42,
          "rank": 2
        },
        {
          "code": "2345",
          "name": "智邦",
          "shares": 6031000.0,
          "weight": "5.750%",
          "weight_value": 5.75,
          "rank": 3
        },
        {
          "code": "2308",
          "name": "台達電",
          "shares": 6024000.0,
          "weight": "5.460%",
          "weight_value": 5.46,
          "rank": 4
        },
        {
          "code": "8046",
          "name": "南電",
          "shares": 12637000.0,
          "weight": "5.320%",
          "weight_value": 5.32,
          "rank": 5
        },
        {
          "code": "3665",
          "name": "貿聯-KY",
          "shares": 4583848.0,
          "weight": "5.310%",
          "weight_value": 5.31,
          "rank": 6
        },
        {
          "code": "3653",
          "name": "健策",
          "shares": 2267000.0,
          "weight": "5.100%",
          "weight_value": 5.1,
          "rank": 7
        },
        {
          "code": "2368",
          "name": "金像電",
          "shares": 8240000.0,
          "weight": "4.790%",
          "weight_value": 4.79,
          "rank": 8
        },
        {
          "code": "2454",
          "name": "聯發科",
          "shares": 4363000.0,
          "weight": "4.770%",
          "weight_value": 4.77,
          "rank": 9
        },
        {
          "code": "3017",
          "name": "奇鋐",
          "shares": 3902000.0,
          "weight": "4.630%",
          "weight_value": 4.63,
          "rank": 10
        }
      ]
    },
    {
      "snapshot_date": "2026-05-03",
      "holdings_count": 50,
      "top_holdings": [
        {
          "code": "2330",
          "name": "台積電",
          "shares": 10039000.0,
          "weight": "8.970%",
          "weight_value": 8.97,
          "rank": 1
        },
        {
          "code": "2383",
          "name": "台光電",
          "shares": 4425000.0,
          "weight": "8.420%",
          "weight_value": 8.42,
          "rank": 2
        },
        {
          "code": "2345",
          "name": "智邦",
          "shares": 6031000.0,
          "weight": "5.750%",
          "weight_value": 5.75,
          "rank": 3
        },
        {
          "code": "2308",
          "name": "台達電",
          "shares": 6024000.0,
          "weight": "5.460%",
          "weight_value": 5.46,
          "rank": 4
        },
        {
          "code": "8046",
          "name": "南電",
          "shares": 12637000.0,
          "weight": "5.320%",
          "weight_value": 5.32,
          "rank": 5
        },
        {
          "code": "3665",
          "name": "貿聯-KY",
          "shares": 4583848.0,
          "weight": "5.310%",
          "weight_value": 5.31,
          "rank": 6
        },
        {
          "code": "3653",
          "name": "健策",
          "shares": 2267000.0,
          "weight": "5.100%",
          "weight_value": 5.1,
          "rank": 7
        },
        {
          "code": "2368",
          "name": "金像電",
          "shares": 8240000.0,
          "weight": "4.790%",
          "weight_value": 4.79,
          "rank": 8
        },
        {
          "code": "2454",
          "name": "聯發科",
          "shares": 4363000.0,
          "weight": "4.770%",
          "weight_value": 4.77,
          "rank": 9
        },
        {
          "code": "3017",
          "name": "奇鋐",
          "shares": 3902000.0,
          "weight": "4.630%",
          "weight_value": 4.63,
          "rank": 10
        }
      ]
    }
  ]
}